{
  "project_info": {
    "project_number": "974617715967",
    "project_id": "locally-ceb80",
    "storage_bucket": "locally-ceb80.firebasestorage.app"
  },
  "client": [
    {
      "client_info": {
        "mobilesdk_app_id": "1:974617715967:android:5bc9491c15476728f798ca",
        "android_client_info": {
          "package_name": "com.example.locally"
        }
      },
      "oauth_client": [],
      "api_key": [
        {
          "current_key": "AIzaSyBNPmk1cpmkddEovxGAKrSFPQAwC6spTwE"
        }
      ],
      "services": {
        "appinvite_service": {
          "other_platform_oauth_client": []
        }
      }
    }
  ],
  "configuration_version": "1"
}